{
"meta":{"test_sets":[],"test_metrics":[],"learn_metrics":[{"best_value":"Min","name":"RMSE"}],"launch_mode":"Train","parameters":"","iteration_count":200,"learn_sets":["learn"],"name":"experiment"},
"iterations":[
{"learn":[8.51753694],"iteration":0,"passed_time":0.00267183478,"remaining_time":0.5316951212},
{"learn":[8.019262901],"iteration":1,"passed_time":0.005955845595,"remaining_time":0.5896287139},
{"learn":[7.608938894],"iteration":2,"passed_time":0.008738821263,"remaining_time":0.573849263},
{"learn":[7.225769582],"iteration":3,"passed_time":0.01590752786,"remaining_time":0.779468865},
{"learn":[6.858203856],"iteration":4,"passed_time":0.01909099337,"remaining_time":0.7445487413},
{"learn":[6.558984404],"iteration":5,"passed_time":0.02193651213,"remaining_time":0.7092805588},
{"learn":[6.265472944],"iteration":6,"passed_time":0.02457765259,"remaining_time":0.6776409927},
{"learn":[5.982869191],"iteration":7,"passed_time":0.02743031354,"remaining_time":0.658327525},
{"learn":[5.755229326],"iteration":8,"passed_time":0.02982442082,"remaining_time":0.6329404864},
{"learn":[5.477559806],"iteration":9,"passed_time":0.03242904537,"remaining_time":0.616151862},
{"learn":[5.218720353],"iteration":10,"passed_time":0.03699896712,"remaining_time":0.635709526},
{"learn":[5.02115692],"iteration":11,"passed_time":0.03960573079,"remaining_time":0.6204897824},
{"learn":[4.817456367],"iteration":12,"passed_time":0.04276913242,"remaining_time":0.6152175202},
{"learn":[4.657713916],"iteration":13,"passed_time":0.04825172662,"remaining_time":0.6410586537},
{"learn":[4.520535489],"iteration":14,"passed_time":0.05135472926,"remaining_time":0.6333749943},
{"learn":[4.349429546],"iteration":15,"passed_time":0.0543300507,"remaining_time":0.6247955831},
{"learn":[4.206974655],"iteration":16,"passed_time":0.05703681912,"remaining_time":0.6139845823},
{"learn":[4.085160669],"iteration":17,"passed_time":0.05942661465,"remaining_time":0.6008691037},
{"learn":[3.964944223],"iteration":18,"passed_time":0.06201976306,"remaining_time":0.5908198481},
{"learn":[3.868032104],"iteration":19,"passed_time":0.06555464073,"remaining_time":0.5899917665},
{"learn":[3.766424586],"iteration":20,"passed_time":0.06841518997,"remaining_time":0.5831580478},
{"learn":[3.697394869],"iteration":21,"passed_time":0.07091972736,"remaining_time":0.5738050668},
{"learn":[3.61535568],"iteration":22,"passed_time":0.07322978529,"remaining_time":0.5635509564},
{"learn":[3.531046044],"iteration":23,"passed_time":0.07613619515,"remaining_time":0.5583320978},
{"learn":[3.466706532],"iteration":24,"passed_time":0.0782782585,"remaining_time":0.5479478095},
{"learn":[3.406286057],"iteration":25,"passed_time":0.08058487617,"remaining_time":0.5392987867},
{"learn":[3.338298979],"iteration":26,"passed_time":0.08276318425,"remaining_time":0.5302974398},
{"learn":[3.286297202],"iteration":27,"passed_time":0.08492142755,"remaining_time":0.5216601978},
{"learn":[3.227264622],"iteration":28,"passed_time":0.08691917701,"remaining_time":0.5125234231},
{"learn":[3.171026902],"iteration":29,"passed_time":0.09026406987,"remaining_time":0.5114963959},
{"learn":[3.129440068],"iteration":30,"passed_time":0.09288048066,"remaining_time":0.5063484268},
{"learn":[3.088309273],"iteration":31,"passed_time":0.09503889781,"remaining_time":0.4989542135},
{"learn":[3.039863279],"iteration":32,"passed_time":0.09707220387,"remaining_time":0.4912441832},
{"learn":[2.990395006],"iteration":33,"passed_time":0.09903984665,"remaining_time":0.4835474866},
{"learn":[2.951038104],"iteration":34,"passed_time":0.101862381,"remaining_time":0.4802083676},
{"learn":[2.91778799],"iteration":35,"passed_time":0.1082692225,"remaining_time":0.4932264579},
{"learn":[2.874548759],"iteration":36,"passed_time":0.111218505,"remaining_time":0.4899626029},
{"learn":[2.83484985],"iteration":37,"passed_time":0.1132946832,"remaining_time":0.4829931231},
{"learn":[2.800094025],"iteration":38,"passed_time":0.115349314,"remaining_time":0.4761856295},
{"learn":[2.760471175],"iteration":39,"passed_time":0.1176073741,"remaining_time":0.4704294966},
{"learn":[2.725594197],"iteration":40,"passed_time":0.1198853076,"remaining_time":0.4649210709},
{"learn":[2.691696661],"iteration":41,"passed_time":0.122057919,"remaining_time":0.4591702668},
{"learn":[2.652763217],"iteration":42,"passed_time":0.1250551949,"remaining_time":0.4565968745},
{"learn":[2.625455085],"iteration":43,"passed_time":0.1282479775,"remaining_time":0.4546973749},
{"learn":[2.598628823],"iteration":44,"passed_time":0.1306961493,"remaining_time":0.4501756252},
{"learn":[2.572642847],"iteration":45,"passed_time":0.1334594377,"remaining_time":0.4467989871},
{"learn":[2.545514045],"iteration":46,"passed_time":0.1364972226,"remaining_time":0.4443420224},
{"learn":[2.523966367],"iteration":47,"passed_time":0.1387544638,"remaining_time":0.4393891352},
{"learn":[2.500980603],"iteration":48,"passed_time":0.1407313005,"remaining_time":0.4336821709},
{"learn":[2.480514847],"iteration":49,"passed_time":0.1427080589,"remaining_time":0.4281241767},
{"learn":[2.456885777],"iteration":50,"passed_time":0.1447559287,"remaining_time":0.4229143798},
{"learn":[2.437126893],"iteration":51,"passed_time":0.147217981,"remaining_time":0.4190050227},
{"learn":[2.415015958],"iteration":52,"passed_time":0.1505397468,"remaining_time":0.4175347694},
{"learn":[2.394099428],"iteration":53,"passed_time":0.1526112805,"remaining_time":0.4126156844},
{"learn":[2.37322156],"iteration":54,"passed_time":0.1545497981,"remaining_time":0.4074494678},
{"learn":[2.352407295],"iteration":55,"passed_time":0.1566551061,"remaining_time":0.4028274156},
{"learn":[2.330995356],"iteration":56,"passed_time":0.1590308766,"remaining_time":0.3989721993},
{"learn":[2.319639449],"iteration":57,"passed_time":0.1609563716,"remaining_time":0.3940655994},
{"learn":[2.301120368],"iteration":58,"passed_time":0.163005883,"remaining_time":0.3895564321},
{"learn":[2.281682644],"iteration":59,"passed_time":0.1654609501,"remaining_time":0.3860755503},
{"learn":[2.268790521],"iteration":60,"passed_time":0.1673544184,"remaining_time":0.3813485928},
{"learn":[2.253168814],"iteration":61,"passed_time":0.1690992017,"remaining_time":0.3763820942},
{"learn":[2.232838504],"iteration":62,"passed_time":0.1710023882,"remaining_time":0.3718623363},
{"learn":[2.219381981],"iteration":63,"passed_time":0.1728567392,"remaining_time":0.3673205708},
{"learn":[2.202356521],"iteration":64,"passed_time":0.1747701473,"remaining_time":0.3629841521},
{"learn":[2.184545875],"iteration":65,"passed_time":0.1783894447,"remaining_time":0.3621846301},
{"learn":[2.16562403],"iteration":66,"passed_time":0.180635399,"remaining_time":0.3585747472},
{"learn":[2.154318435],"iteration":67,"passed_time":0.1825559461,"remaining_time":0.3543733071},
{"learn":[2.140146729],"iteration":68,"passed_time":0.1842491196,"remaining_time":0.3498062996},
{"learn":[2.124972361],"iteration":69,"passed_time":0.1876763841,"remaining_time":0.3485418561},
{"learn":[2.107070215],"iteration":70,"passed_time":0.1898862394,"remaining_time":0.3450045758},
{"learn":[2.094465853],"iteration":71,"passed_time":0.1922167257,"remaining_time":0.3417186234},
{"learn":[2.081860863],"iteration":72,"passed_time":0.1943043166,"remaining_time":0.3380362769},
{"learn":[2.07164964],"iteration":73,"passed_time":0.1968279722,"remaining_time":0.3351395202},
{"learn":[2.049273735],"iteration":74,"passed_time":0.1988412904,"remaining_time":0.3314021507},
{"learn":[2.038700741],"iteration":75,"passed_time":0.2007265979,"remaining_time":0.3275012912},
{"learn":[2.030304506],"iteration":76,"passed_time":0.2026547195,"remaining_time":0.3237211753},
{"learn":[2.01478638],"iteration":77,"passed_time":0.205507625,"remaining_time":0.3214350031},
{"learn":[2.003309465],"iteration":78,"passed_time":0.2078212033,"remaining_time":0.3183084253},
{"learn":[1.989841788],"iteration":79,"passed_time":0.2118760749,"remaining_time":0.3178141123},
{"learn":[1.981309639],"iteration":80,"passed_time":0.2145283922,"remaining_time":0.3151713416},
{"learn":[1.968427999],"iteration":81,"passed_time":0.2164597536,"remaining_time":0.3114908649},
{"learn":[1.963038623],"iteration":82,"passed_time":0.2183733174,"remaining_time":0.3078274475},
{"learn":[1.953128829],"iteration":83,"passed_time":0.2212545662,"remaining_time":0.30554202},
{"learn":[1.944585008],"iteration":84,"passed_time":0.2243146373,"remaining_time":0.3034845093},
{"learn":[1.9281853],"iteration":85,"passed_time":0.227983227,"remaining_time":0.3022103241},
{"learn":[1.91479698],"iteration":86,"passed_time":0.2301193288,"remaining_time":0.2988906225},
{"learn":[1.895517336],"iteration":87,"passed_time":0.2316429703,"remaining_time":0.2948183259},
{"learn":[1.883751545],"iteration":88,"passed_time":0.2338169246,"remaining_time":0.2916143666},
{"learn":[1.877634188],"iteration":89,"passed_time":0.2378807732,"remaining_time":0.2907431673},
{"learn":[1.862916287],"iteration":90,"passed_time":0.2400465223,"remaining_time":0.2875282519},
{"learn":[1.850894645],"iteration":91,"passed_time":0.2422243219,"remaining_time":0.284350291},
{"learn":[1.842166461],"iteration":92,"passed_time":0.2440558773,"remaining_time":0.2807954717},
{"learn":[1.824675201],"iteration":93,"passed_time":0.2459302179,"remaining_time":0.2773255649},
{"learn":[1.812995101],"iteration":94,"passed_time":0.2482732741,"remaining_time":0.274407303},
{"learn":[1.803957192],"iteration":95,"passed_time":0.2518775595,"remaining_time":0.2728673562},
{"learn":[1.793437715],"iteration":96,"passed_time":0.2548689373,"remaining_time":0.2706340262},
{"learn":[1.784918494],"iteration":97,"passed_time":0.2569539491,"remaining_time":0.2674418654},
{"learn":[1.772107771],"iteration":98,"passed_time":0.2589324311,"remaining_time":0.2641633893},
{"learn":[1.76239984],"iteration":99,"passed_time":0.2608421078,"remaining_time":0.2608421078},
{"learn":[1.752291407],"iteration":100,"passed_time":0.2629615123,"remaining_time":0.2577543536},
{"learn":[1.745030077],"iteration":101,"passed_time":0.2667204813,"remaining_time":0.2562608545},
{"learn":[1.731300542],"iteration":102,"passed_time":0.2693926895,"remaining_time":0.2536999115},
{"learn":[1.720383462],"iteration":103,"passed_time":0.2737451741,"remaining_time":0.252687853},
{"learn":[1.706474105],"iteration":104,"passed_time":0.275870636,"remaining_time":0.2495972421},
{"learn":[1.697735838],"iteration":105,"passed_time":0.2777283363,"remaining_time":0.2462873926},
{"learn":[1.686275667],"iteration":106,"passed_time":0.27999332,"remaining_time":0.24335868},
{"learn":[1.680345044],"iteration":107,"passed_time":0.2822924247,"remaining_time":0.2404713247},
{"learn":[1.668159505],"iteration":108,"passed_time":0.2840503221,"remaining_time":0.2371429295},
{"learn":[1.656473623],"iteration":109,"passed_time":0.2861509846,"remaining_time":0.2341235329},
{"learn":[1.645427308],"iteration":110,"passed_time":0.2877767705,"remaining_time":0.2307399331},
{"learn":[1.639058868],"iteration":111,"passed_time":0.2896470837,"remaining_time":0.2275798514},
{"learn":[1.627894586],"iteration":112,"passed_time":0.2914919537,"remaining_time":0.2244230086},
{"learn":[1.61939707],"iteration":113,"passed_time":0.2932974936,"remaining_time":0.2212595128},
{"learn":[1.61369416],"iteration":114,"passed_time":0.2957484451,"remaining_time":0.2185966768},
{"learn":[1.607803602],"iteration":115,"passed_time":0.2975727175,"remaining_time":0.215483692},
{"learn":[1.601214128],"iteration":116,"passed_time":0.29964613,"remaining_time":0.2125694769},
{"learn":[1.591182829],"iteration":117,"passed_time":0.3016838452,"remaining_time":0.209644706},
{"learn":[1.581004805],"iteration":118,"passed_time":0.303779401,"remaining_time":0.2067742141},
{"learn":[1.571613907],"iteration":119,"passed_time":0.305575584,"remaining_time":0.203717056},
{"learn":[1.56439448],"iteration":120,"passed_time":0.3073798935,"remaining_time":0.2006860462},
{"learn":[1.559303079],"iteration":121,"passed_time":0.3094310523,"remaining_time":0.1978329679},
{"learn":[1.55184421],"iteration":122,"passed_time":0.3112723838,"remaining_time":0.1948615736},
{"learn":[1.543683106],"iteration":123,"passed_time":0.3128334214,"remaining_time":0.1917366131},
{"learn":[1.536282983],"iteration":124,"passed_time":0.3145405542,"remaining_time":0.1887243325},
{"learn":[1.528608999],"iteration":125,"passed_time":0.3170025413,"remaining_time":0.1861760957},
{"learn":[1.52280592],"iteration":126,"passed_time":0.3195047295,"remaining_time":0.1836523249},
{"learn":[1.514851357],"iteration":127,"passed_time":0.3228816948,"remaining_time":0.1816209533},
{"learn":[1.509220614],"iteration":128,"passed_time":0.3254218345,"remaining_time":0.1791081415},
{"learn":[1.504361022],"iteration":129,"passed_time":0.3272609187,"remaining_time":0.1762174178},
{"learn":[1.497597733],"iteration":130,"passed_time":0.3290243118,"remaining_time":0.1733028818},
{"learn":[1.49171317],"iteration":131,"passed_time":0.3307226473,"remaining_time":0.1703722729},
{"learn":[1.487578519],"iteration":132,"passed_time":0.332384935,"remaining_time":0.1674420349},
{"learn":[1.478330661],"iteration":133,"passed_time":0.3339389924,"remaining_time":0.1644774142},
{"learn":[1.472067257],"iteration":134,"passed_time":0.3363118538,"remaining_time":0.1619279296},
{"learn":[1.467551145],"iteration":135,"passed_time":0.3385011472,"remaining_time":0.1592946575},
{"learn":[1.460608189],"iteration":136,"passed_time":0.3405628346,"remaining_time":0.1566091867},
{"learn":[1.454342198],"iteration":137,"passed_time":0.3425496721,"remaining_time":0.153899128},
{"learn":[1.447503831],"iteration":138,"passed_time":0.3444565926,"remaining_time":0.151164404},
{"learn":[1.440482914],"iteration":139,"passed_time":0.3466238583,"remaining_time":0.1485530821},
{"learn":[1.434186771],"iteration":140,"passed_time":0.348836813,"remaining_time":0.1459671771},
{"learn":[1.42892271],"iteration":141,"passed_time":0.3516797476,"remaining_time":0.1436438406},
{"learn":[1.426296509],"iteration":142,"passed_time":0.3535227995,"remaining_time":0.1409146823},
{"learn":[1.420536283],"iteration":143,"passed_time":0.355170992,"remaining_time":0.1381220525},
{"learn":[1.415896163],"iteration":144,"passed_time":0.357708223,"remaining_time":0.1356824294},
{"learn":[1.411287282],"iteration":145,"passed_time":0.3599805825,"remaining_time":0.1331435031},
{"learn":[1.4038903],"iteration":146,"passed_time":0.3617686083,"remaining_time":0.1304335799},
{"learn":[1.401151315],"iteration":147,"passed_time":0.3636024015,"remaining_time":0.1277521951},
{"learn":[1.396542447],"iteration":148,"passed_time":0.3658950952,"remaining_time":0.1252392608},
{"learn":[1.391968423],"iteration":149,"passed_time":0.3680143697,"remaining_time":0.1226714566},
{"learn":[1.390396409],"iteration":150,"passed_time":0.3698457136,"remaining_time":0.1200161587},
{"learn":[1.384886458],"iteration":151,"passed_time":0.3716530889,"remaining_time":0.1173641334},
{"learn":[1.378687647],"iteration":152,"passed_time":0.3733956702,"remaining_time":0.1147032451},
{"learn":[1.367371573],"iteration":153,"passed_time":0.3750261703,"remaining_time":0.1120208041},
{"learn":[1.360639648],"iteration":154,"passed_time":0.3766436826,"remaining_time":0.1093481659},
{"learn":[1.354344111],"iteration":155,"passed_time":0.3794241388,"remaining_time":0.1070170648},
{"learn":[1.350505516],"iteration":156,"passed_time":0.381335219,"remaining_time":0.1044421301},
{"learn":[1.345622683],"iteration":157,"passed_time":0.3830103424,"remaining_time":0.1018128758},
{"learn":[1.339176054],"iteration":158,"passed_time":0.3846456387,"remaining_time":0.09918535337},
{"learn":[1.33181321],"iteration":159,"passed_time":0.3864417239,"remaining_time":0.09661043098},
{"learn":[1.327126614],"iteration":160,"passed_time":0.3883744765,"remaining_time":0.09407828934},
{"learn":[1.323217062],"iteration":161,"passed_time":0.390377646,"remaining_time":0.09157006511},
{"learn":[1.318865771],"iteration":162,"passed_time":0.3926240277,"remaining_time":0.08912324555},
{"learn":[1.312148538],"iteration":163,"passed_time":0.3947365244,"remaining_time":0.08664948098},
{"learn":[1.309209997],"iteration":164,"passed_time":0.3963638002,"remaining_time":0.08407716974},
{"learn":[1.301822239],"iteration":165,"passed_time":0.3979778854,"remaining_time":0.08151354279},
{"learn":[1.294678024],"iteration":166,"passed_time":0.4000711603,"remaining_time":0.07905597779},
{"learn":[1.287351128],"iteration":167,"passed_time":0.4019465821,"remaining_time":0.07656125373},
{"learn":[1.280933574],"iteration":168,"passed_time":0.4034631384,"remaining_time":0.07400803131},
{"learn":[1.278443887],"iteration":169,"passed_time":0.405257822,"remaining_time":0.07151608624},
{"learn":[1.27133607],"iteration":170,"passed_time":0.4071428787,"remaining_time":0.0690476227},
{"learn":[1.264733002],"iteration":171,"passed_time":0.4087593108,"remaining_time":0.06654221338},
{"learn":[1.260445876],"iteration":172,"passed_time":0.4100931988,"remaining_time":0.06400298479},
{"learn":[1.254785438],"iteration":173,"passed_time":0.4121972753,"remaining_time":0.06159269631},
{"learn":[1.24941415],"iteration":174,"passed_time":0.4145116917,"remaining_time":0.05921595595},
{"learn":[1.246568252],"iteration":175,"passed_time":0.4163423008,"remaining_time":0.05677395011},
{"learn":[1.243185795],"iteration":176,"passed_time":0.4179629233,"remaining_time":0.05431156631},
{"learn":[1.236262441],"iteration":177,"passed_time":0.4196120259,"remaining_time":0.0518621605},
{"learn":[1.228192914],"iteration":178,"passed_time":0.4213814121,"remaining_time":0.04943580813},
{"learn":[1.223569951],"iteration":179,"passed_time":0.4229251288,"remaining_time":0.04699168098},
{"learn":[1.216417424],"iteration":180,"passed_time":0.4244975524,"remaining_time":0.04456051655},
{"learn":[1.211991582],"iteration":181,"passed_time":0.4260408033,"remaining_time":0.04213590362},
{"learn":[1.20608334],"iteration":182,"passed_time":0.4275394543,"remaining_time":0.03971677991},
{"learn":[1.203728523],"iteration":183,"passed_time":0.4289134656,"remaining_time":0.0372968231},
{"learn":[1.199600577],"iteration":184,"passed_time":0.4304201499,"remaining_time":0.03489893107},
{"learn":[1.191887283],"iteration":185,"passed_time":0.4323983049,"remaining_time":0.03254610897},
{"learn":[1.187922633],"iteration":186,"passed_time":0.4339364336,"remaining_time":0.03016670394},
{"learn":[1.183929515],"iteration":187,"passed_time":0.4358768264,"remaining_time":0.02782192509},
{"learn":[1.181034419],"iteration":188,"passed_time":0.4374665649,"remaining_time":0.02546101701},
{"learn":[1.175784097],"iteration":189,"passed_time":0.4390520976,"remaining_time":0.02310800514},
{"learn":[1.173183433],"iteration":190,"passed_time":0.4405810464,"remaining_time":0.02076036344},
{"learn":[1.168236792],"iteration":191,"passed_time":0.4420431698,"remaining_time":0.01841846541},
{"learn":[1.163598938],"iteration":192,"passed_time":0.4433462852,"remaining_time":0.01607991708},
{"learn":[1.159227052],"iteration":193,"passed_time":0.4449285701,"remaining_time":0.01376067742},
{"learn":[1.152756719],"iteration":194,"passed_time":0.4464244179,"remaining_time":0.01144677995},
{"learn":[1.14795106],"iteration":195,"passed_time":0.4477359893,"remaining_time":0.009137469169},
{"learn":[1.145962039],"iteration":196,"passed_time":0.4495203073,"remaining_time":0.006845486913},
{"learn":[1.141672802],"iteration":197,"passed_time":0.4513179798,"remaining_time":0.004558767473},
{"learn":[1.135345347],"iteration":198,"passed_time":0.4528948944,"remaining_time":0.002275853741},
{"learn":[1.13208386],"iteration":199,"passed_time":0.4543263017,"remaining_time":0}
]}